{
  "id": "pi-network",
  "symbol": "pi",
  "name": "Pi Network",
  "priceGBP": 0.45627,
  "marketCapGBP": 3350460776,
  "percentageChange": -4.55826,
  "high_24hGBP": 0.478724,
  "low_24hGBP": 0.446258,
  "lastUpdated": "2025-06-06T06:08:23.908Z",
  "allTimeHigh": {
    "priceGBP": 2.35,
    "percentageChange": -80.60675,
    "date": "2025-02-26T16:41:03.732Z"
  },
  "allTimeLow": {
    "priceGBP": 0.315895,
    "percentageChange": 44.44515,
    "date": "2025-04-05T04:50:37.033Z"
  },
  "priceChange": {
    "pricePi_24h": -0.02955987324721,
    "priceGBP24h": -0.022232865193015428,
    "percentageChangePi_24h": -4.55826,
    "percentageChangePi_7d": -8.84068,
    "percentageChangePi_14d": -23.59298,
    "percentageChangePi_30d": 6.80695,
    "percentageChangePi_60d": 11.23266,
    "percentageChangePi_200d": 0.0,
    "percentageChangePi_1y": 0.0,
    "percentageChangePi_GBP": -4.64634,
    "percentageChangePi_GBP_7d": -9.41673,
    "percentageChangePi_GBP_14d": -24.20106,
    "percentageChangePi_GBP_30d": 5.14967,
    "percentageChangePi_GBP_60d": 5.9766,
    "percentageChangePi_GBP_200d": null,
    "percentageChangePi_GBP_1y": null
  }
}
