{
  "pi-network": {
    "id": "pi-network",
    "symbol": "pi",
    "name": "Pi Network",
    "priceGBP": 0.099196,
    "marketCapGBP": 1065804119,
    "percentageChange": 3.55752,
    "high_24hGBP": 0.102739,
    "low_24hGBP": 0.095463,
    "lastUpdated": "2026-06-14T12:47:28.630Z",
    "allTimeHigh": {
      "priceGBP": 2.35,
      "percentageChange": -95.7858,
      "date": "2025-02-26T16:41:03.732Z"
    },
    "allTimeLow": {
      "priceGBP": 0.089087,
      "percentageChange": 11.29998,
      "date": "2026-06-06T05:05:45.511Z"
    },
    "priceChange": {
      "pricePi_24h": 0.00455454,
      "priceGBP24h": 0.0037184,
      "percentageChangePi_24h": 3.55752,
      "percentageChangePi_7d": 2.48106,
      "percentageChangePi_14d": -10.0644,
      "percentageChangePi_30d": -21.8287,
      "percentageChangePi_60d": -20.44702,
      "percentageChangePi_200d": -47.34524,
      "percentageChangePi_1y": -77.3126,
      "percentageChangePi_GBP": 3.89453,
      "percentageChangePi_GBP_7d": 2.67277,
      "percentageChangePi_GBP_14d": -9.47895,
      "percentageChangePi_GBP_30d": -21.82305,
      "percentageChangePi_GBP_60d": -19.35559,
      "percentageChangePi_GBP_200d": -48.13111,
      "percentageChangePi_GBP_1y": -76.97395
    }
  },
  "xrp": {
    "id": "ripple",
    "symbol": "xrp",
    "name": "XRP",
    "priceGBP": 0.851737,
    "marketCapGBP": 52854527455,
    "percentageChange": -1.12489,
    "high_24hGBP": 0.863022,
    "low_24hGBP": 0.851722,
    "lastUpdated": "2026-06-14T12:46:52.205Z",
    "allTimeHigh": {
      "priceGBP": 2.76,
      "percentageChange": -69.18851,
      "date": "2025-01-16T17:00:22.630Z"
    },
    "allTimeLow": {
      "priceGBP": 0.00159246,
      "percentageChange": 53385.46345,
      "date": "2014-05-22T00:00:00.000Z"
    },
    "priceChange": {
      "pricePi_24h": -0.012951312014733,
      "priceGBP24h": -0.006895804617357615,
      "percentageChangePi_24h": -1.12489,
      "percentageChangePi_7d": 0.39013,
      "percentageChangePi_14d": -14.6318,
      "percentageChangePi_30d": -22.53377,
      "percentageChangePi_60d": -16.35943,
      "percentageChangePi_200d": -47.56473,
      "percentageChangePi_1y": -47.55077,
      "percentageChangePi_GBP": -0.80311,
      "percentageChangePi_GBP_7d": 0.57792,
      "percentageChangePi_GBP_14d": -14.07608,
      "percentageChangePi_GBP_30d": -22.52818,
      "percentageChangePi_GBP_60d": -15.17031,
      "percentageChangePi_GBP_200d": -48.31146,
      "percentageChangePi_GBP_1y": -46.76787
    }
  }
}
