{
  "pi-network": {
    "id": "pi-network",
    "symbol": "pi",
    "name": "Pi Network",
    "priceGBP": 0.177398,
    "marketCapGBP": 1463441010,
    "percentageChange": -0.32189,
    "high_24hGBP": 0.182017,
    "low_24hGBP": 0.174034,
    "lastUpdated": "2025-10-09T06:09:23.054Z",
    "allTimeHigh": {
      "priceGBP": 2.35,
      "percentageChange": -92.4594,
      "date": "2025-02-26T16:41:03.732Z"
    },
    "allTimeLow": {
      "priceGBP": 0.174034,
      "percentageChange": 1.94488,
      "date": "2025-10-08T12:41:50.803Z"
    },
    "priceChange": {
      "pricePi_24h": -0.0007679062930494,
      "priceGBP24h": -0.000756559728844586,
      "percentageChangePi_24h": -0.32189,
      "percentageChangePi_7d": -12.06887,
      "percentageChangePi_14d": -13.22664,
      "percentageChangePi_30d": -30.80933,
      "percentageChangePi_60d": -44.46153,
      "percentageChangePi_200d": -76.47366,
      "percentageChangePi_1y": 0.0,
      "percentageChangePi_GBP": -0.42466,
      "percentageChangePi_GBP_7d": -11.60117,
      "percentageChangePi_GBP_14d": -12.84731,
      "percentageChangePi_GBP_30d": -29.92895,
      "percentageChangePi_GBP_60d": -44.26534,
      "percentageChangePi_GBP_200d": -77.32602,
      "percentageChangePi_GBP_1y": null
    }
  },
  "xrp": {
    "id": "ripple",
    "symbol": "xrp",
    "name": "XRP",
    "priceGBP": 2.11,
    "marketCapGBP": 126503842887,
    "percentageChange": -0.61449,
    "high_24hGBP": 2.18,
    "low_24hGBP": 2.11,
    "lastUpdated": "2025-10-09T06:09:23.072Z",
    "allTimeHigh": {
      "priceGBP": 2.76,
      "percentageChange": -23.57783,
      "date": "2025-01-16T17:00:22.630Z"
    },
    "allTimeLow": {
      "priceGBP": 0.00159246,
      "percentageChange": 132560.73307,
      "date": "2014-05-22T00:00:00.000Z"
    },
    "priceChange": {
      "pricePi_24h": -0.017501809221498,
      "priceGBP24h": -0.015161346098394368,
      "percentageChangePi_24h": -0.61449,
      "percentageChangePi_7d": -4.59686,
      "percentageChangePi_14d": -0.42247,
      "percentageChangePi_30d": -4.50389,
      "percentageChangePi_60d": -13.45353,
      "percentageChangePi_200d": 18.80761,
      "percentageChangePi_1y": 431.11084,
      "percentageChangePi_GBP": -0.71284,
      "percentageChangePi_GBP_7d": -4.09329,
      "percentageChangePi_GBP_14d": 0.01027,
      "percentageChangePi_GBP_30d": -3.2888,
      "percentageChangePi_GBP_60d": -13.14781,
      "percentageChangePi_GBP_200d": 14.50321,
      "percentageChangePi_GBP_1y": 418.7731
    }
  }
}
