{
  "pi-network": {
    "id": "pi-network",
    "symbol": "pi",
    "name": "Pi Network",
    "priceGBP": 0.265731,
    "marketCapGBP": 2161826769,
    "percentageChange": -0.02663,
    "high_24hGBP": 0.267568,
    "low_24hGBP": 0.262454,
    "lastUpdated": "2025-09-19T06:08:54.208Z",
    "allTimeHigh": {
      "priceGBP": 2.35,
      "percentageChange": -88.70599,
      "date": "2025-02-26T16:41:03.732Z"
    },
    "allTimeLow": {
      "priceGBP": 0.245655,
      "percentageChange": 8.17239,
      "date": "2025-08-26T00:57:49.575Z"
    },
    "priceChange": {
      "pricePi_24h": -0.000095794235003,
      "priceGBP24h": 0.00111723,
      "percentageChangePi_24h": -0.02663,
      "percentageChangePi_7d": 2.206,
      "percentageChangePi_14d": 3.23502,
      "percentageChangePi_30d": 3.00291,
      "percentageChangePi_60d": -19.91168,
      "percentageChangePi_200d": -78.75883,
      "percentageChangePi_1y": 0.0,
      "percentageChangePi_GBP": 0.42221,
      "percentageChangePi_GBP_7d": 2.38819,
      "percentageChangePi_GBP_14d": 2.70343,
      "percentageChangePi_GBP_30d": 2.62808,
      "percentageChangePi_GBP_60d": -20.54837,
      "percentageChangePi_GBP_200d": -80.21924,
      "percentageChangePi_GBP_1y": null
    }
  },
  "xrp": {
    "id": "ripple",
    "symbol": "xrp",
    "name": "XRP",
    "priceGBP": 2.25,
    "marketCapGBP": 134474946397,
    "percentageChange": -1.12446,
    "high_24hGBP": 2.31,
    "low_24hGBP": 2.23,
    "lastUpdated": "2025-09-19T06:08:23.158Z",
    "allTimeHigh": {
      "priceGBP": 2.76,
      "percentageChange": -18.59932,
      "date": "2025-01-16T17:00:22.630Z"
    },
    "allTimeLow": {
      "priceGBP": 0.00159246,
      "percentageChange": 141202.89354,
      "date": "2014-05-22T00:00:00.000Z"
    },
    "priceChange": {
      "pricePi_24h": -0.034601095244938,
      "priceGBP24h": -0.015406279519880162,
      "percentageChangePi_24h": -1.12446,
      "percentageChangePi_7d": -0.36784,
      "percentageChangePi_14d": 8.16185,
      "percentageChangePi_30d": 4.95319,
      "percentageChangePi_60d": -13.14601,
      "percentageChangePi_200d": 8.22174,
      "percentageChangePi_1y": 417.76713,
      "percentageChangePi_GBP": -0.68054,
      "percentageChangePi_GBP_7d": -0.19024,
      "percentageChangePi_GBP_14d": 7.60489,
      "percentageChangePi_GBP_30d": 4.57126,
      "percentageChangePi_GBP_60d": -13.87337,
      "percentageChangePi_GBP_200d": 0.78108,
      "percentageChangePi_GBP_1y": 405.48761
    }
  }
}
