{
  "pi-network": {
    "id": "pi-network",
    "symbol": "pi",
    "name": "Pi Network",
    "priceGBP": 0.204311,
    "marketCapGBP": 1706894047,
    "percentageChange": 5.95753,
    "high_24hGBP": 0.207713,
    "low_24hGBP": 0.189558,
    "lastUpdated": "2025-11-27T18:08:30.485Z",
    "allTimeHigh": {
      "priceGBP": 2.35,
      "percentageChange": -91.31438,
      "date": "2025-02-26T16:41:03.732Z"
    },
    "allTimeLow": {
      "priceGBP": 0.128875,
      "percentageChange": 58.57149,
      "date": "2025-10-10T21:25:41.582Z"
    },
    "priceChange": {
      "pricePi_24h": 0.01520682,
      "priceGBP24h": 0.01134482,
      "percentageChangePi_24h": 5.95753,
      "percentageChangePi_7d": 14.20543,
      "percentageChangePi_14d": 22.69906,
      "percentageChangePi_30d": 4.28855,
      "percentageChangePi_60d": 1.04713,
      "percentageChangePi_200d": -74.71489,
      "percentageChangePi_1y": 0.0,
      "percentageChangePi_GBP": 5.87918,
      "percentageChangePi_GBP_7d": 12.86037,
      "percentageChangePi_GBP_14d": 22.43795,
      "percentageChangePi_GBP_30d": 4.59523,
      "percentageChangePi_GBP_60d": 2.51878,
      "percentageChangePi_GBP_200d": -74.59879,
      "percentageChangePi_GBP_1y": null
    }
  },
  "xrp": {
    "id": "ripple",
    "symbol": "xrp",
    "name": "XRP",
    "priceGBP": 1.67,
    "marketCapGBP": 100587815737,
    "percentageChange": -1.37801,
    "high_24hGBP": 1.7,
    "low_24hGBP": 1.64,
    "lastUpdated": "2025-11-27T18:08:20.443Z",
    "allTimeHigh": {
      "priceGBP": 2.76,
      "percentageChange": -39.68365,
      "date": "2025-01-16T17:00:22.630Z"
    },
    "allTimeLow": {
      "priceGBP": 0.00159246,
      "percentageChange": 104602.75397,
      "date": "2014-05-22T00:00:00.000Z"
    },
    "priceChange": {
      "pricePi_24h": -0.030858496105016,
      "priceGBP24h": -0.024562861881779252,
      "percentageChangePi_24h": -1.37801,
      "percentageChangePi_7d": 9.84345,
      "percentageChangePi_14d": -7.95467,
      "percentageChangePi_30d": -16.6487,
      "percentageChangePi_60d": -21.82611,
      "percentageChangePi_200d": -5.91415,
      "percentageChangePi_1y": 49.69567,
      "percentageChangePi_GBP": -1.45093,
      "percentageChangePi_GBP_7d": 8.54976,
      "percentageChangePi_GBP_14d": -8.13246,
      "percentageChangePi_GBP_30d": -16.32937,
      "percentageChangePi_GBP_60d": -20.68758,
      "percentageChangePi_GBP_200d": -5.48211,
      "percentageChangePi_GBP_1y": 43.36182
    }
  }
}
