{
  "pi-network": {
    "id": "pi-network",
    "symbol": "pi",
    "name": "Pi Network",
    "priceGBP": 0.176928,
    "marketCapGBP": 1466319274,
    "percentageChange": 13.44844,
    "high_24hGBP": 0.176748,
    "low_24hGBP": 0.154862,
    "lastUpdated": "2025-10-27T00:28:45.826Z",
    "allTimeHigh": {
      "priceGBP": 2.35,
      "percentageChange": -92.48793,
      "date": "2025-02-26T16:41:03.732Z"
    },
    "allTimeLow": {
      "priceGBP": 0.128875,
      "percentageChange": 37.14618,
      "date": "2025-10-10T21:25:41.582Z"
    },
    "priceChange": {
      "pricePi_24h": 0.02794,
      "priceGBP24h": 0.02079041,
      "percentageChangePi_24h": 13.44844,
      "percentageChangePi_7d": 14.19384,
      "percentageChangePi_14d": 12.63516,
      "percentageChangePi_30d": -13.47954,
      "percentageChangePi_60d": -31.0114,
      "percentageChangePi_200d": -61.21584,
      "percentageChangePi_1y": 0.0,
      "percentageChangePi_GBP": 13.31545,
      "percentageChangePi_GBP_7d": 15.10621,
      "percentageChangePi_GBP_14d": 12.81401,
      "percentageChangePi_GBP_30d": -12.95658,
      "percentageChangePi_GBP_60d": -30.0876,
      "percentageChangePi_GBP_200d": -62.68065,
      "percentageChangePi_GBP_1y": null
    }
  },
  "xrp": {
    "id": "ripple",
    "symbol": "xrp",
    "name": "XRP",
    "priceGBP": 1.99,
    "marketCapGBP": 119532754580,
    "percentageChange": 1.41666,
    "high_24hGBP": 2.0,
    "low_24hGBP": 1.95,
    "lastUpdated": "2025-10-27T00:29:30.644Z",
    "allTimeHigh": {
      "priceGBP": 2.76,
      "percentageChange": -27.88056,
      "date": "2025-01-16T17:00:22.630Z"
    },
    "allTimeLow": {
      "priceGBP": 0.00159246,
      "percentageChange": 125091.64913,
      "date": "2014-05-22T00:00:00.000Z"
    },
    "priceChange": {
      "pricePi_24h": 0.03706665,
      "priceGBP24h": 0.02551934,
      "percentageChangePi_24h": 1.41666,
      "percentageChangePi_7d": 10.40696,
      "percentageChangePi_14d": 4.68686,
      "percentageChangePi_30d": -4.70469,
      "percentageChangePi_60d": -11.06409,
      "percentageChangePi_200d": 28.47597,
      "percentageChangePi_1y": 418.76377,
      "percentageChangePi_GBP": 1.29778,
      "percentageChangePi_GBP_7d": 11.28908,
      "percentageChangePi_GBP_14d": 4.85308,
      "percentageChangePi_GBP_30d": -4.12869,
      "percentageChangePi_GBP_60d": -9.87829,
      "percentageChangePi_GBP_200d": 23.67342,
      "percentageChangePi_GBP_1y": 404.72132
    }
  }
}
