{
  "pi-network": {
    "id": "pi-network",
    "symbol": "pi",
    "name": "Pi Network",
    "priceGBP": 0.181334,
    "marketCapGBP": 1511116842,
    "percentageChange": -1.77529,
    "high_24hGBP": 0.184643,
    "low_24hGBP": 0.178336,
    "lastUpdated": "2025-11-25T06:09:31.898Z",
    "allTimeHigh": {
      "priceGBP": 2.35,
      "percentageChange": -92.29083,
      "date": "2025-02-26T16:41:03.732Z"
    },
    "allTimeLow": {
      "priceGBP": 0.128875,
      "percentageChange": 40.74462,
      "date": "2025-10-10T21:25:41.582Z"
    },
    "priceChange": {
      "pricePi_24h": -0.0042939584766806,
      "priceGBP24h": -0.00317772022615001,
      "percentageChangePi_24h": -1.77529,
      "percentageChangePi_7d": 6.03571,
      "percentageChangePi_14d": 2.6448,
      "percentageChangePi_30d": 14.97239,
      "percentageChangePi_60d": -9.5292,
      "percentageChangePi_200d": -64.92348,
      "percentageChangePi_1y": 0.0,
      "percentageChangePi_GBP": -1.72224,
      "percentageChangePi_GBP_7d": 6.49854,
      "percentageChangePi_GBP_14d": 3.17171,
      "percentageChangePi_GBP_30d": 16.76396,
      "percentageChangePi_GBP_60d": -7.79479,
      "percentageChangePi_GBP_200d": -64.55948,
      "percentageChangePi_GBP_1y": null
    }
  },
  "xrp": {
    "id": "ripple",
    "symbol": "xrp",
    "name": "XRP",
    "priceGBP": 1.72,
    "marketCapGBP": 103570627541,
    "percentageChange": 8.43575,
    "high_24hGBP": 1.74,
    "low_24hGBP": 1.56,
    "lastUpdated": "2025-11-25T06:09:53.123Z",
    "allTimeHigh": {
      "priceGBP": 2.76,
      "percentageChange": -37.77747,
      "date": "2025-01-16T17:00:22.630Z"
    },
    "allTimeLow": {
      "priceGBP": 0.00159246,
      "percentageChange": 107911.66478,
      "date": "2014-05-22T00:00:00.000Z"
    },
    "priceChange": {
      "pricePi_24h": 0.17505154,
      "priceGBP24h": 0.134208,
      "percentageChangePi_24h": 8.43575,
      "percentageChangePi_7d": 4.64138,
      "percentageChangePi_14d": -10.00786,
      "percentageChangePi_30d": -13.8144,
      "percentageChangePi_60d": -18.51028,
      "percentageChangePi_200d": -2.20248,
      "percentageChangePi_1y": 55.7938,
      "percentageChangePi_GBP": 8.47683,
      "percentageChangePi_GBP_7d": 5.09813,
      "percentageChangePi_GBP_14d": -9.56734,
      "percentageChangePi_GBP_30d": -12.4714,
      "percentageChangePi_GBP_60d": -16.94805,
      "percentageChangePi_GBP_200d": -1.18762,
      "percentageChangePi_GBP_1y": 49.77269
    }
  }
}
