{
  "pi-network": {
    "id": "pi-network",
    "symbol": "pi",
    "name": "Pi Network",
    "priceGBP": 0.113352,
    "marketCapGBP": 996298548,
    "percentageChange": -3.5681,
    "high_24hGBP": 0.118614,
    "low_24hGBP": 0.113648,
    "lastUpdated": "2026-02-03T18:22:53.844Z",
    "allTimeHigh": {
      "priceGBP": 2.35,
      "percentageChange": -95.15814,
      "date": "2025-02-26T16:41:03.732Z"
    },
    "allTimeLow": {
      "priceGBP": 0.110654,
      "percentageChange": 2.95273,
      "date": "2026-02-02T03:40:09.322Z"
    },
    "priceChange": {
      "pricePi_24h": -0.0057423678593255,
      "priceGBP24h": -0.004556907398077181,
      "percentageChangePi_24h": -3.5681,
      "percentageChangePi_7d": -10.79459,
      "percentageChangePi_14d": -15.12517,
      "percentageChangePi_30d": -27.85111,
      "percentageChangePi_60d": -29.77906,
      "percentageChangePi_200d": -65.4586,
      "percentageChangePi_1y": 0.0,
      "percentageChangePi_GBP": -3.86477,
      "percentageChangePi_GBP_7d": -10.21659,
      "percentageChangePi_GBP_14d": -16.57395,
      "percentageChangePi_GBP_30d": -29.03338,
      "percentageChangePi_GBP_60d": -31.6572,
      "percentageChangePi_GBP_200d": -66.1428,
      "percentageChangePi_GBP_1y": null
    }
  },
  "xrp": {
    "id": "ripple",
    "symbol": "xrp",
    "name": "XRP",
    "priceGBP": 1.13,
    "marketCapGBP": 68937027692,
    "percentageChange": -5.40976,
    "high_24hGBP": 1.2,
    "low_24hGBP": 1.13,
    "lastUpdated": "2026-02-03T18:22:40.155Z",
    "allTimeHigh": {
      "priceGBP": 2.76,
      "percentageChange": -59.02662,
      "date": "2025-01-16T17:00:22.630Z"
    },
    "allTimeLow": {
      "priceGBP": 0.00159246,
      "percentageChange": 71025.42049,
      "date": "2014-05-22T00:00:00.000Z"
    },
    "priceChange": {
      "pricePi_24h": -0.088689533129672,
      "priceGBP24h": -0.0684730598071106,
      "percentageChangePi_24h": -5.40976,
      "percentageChangePi_7d": -18.7865,
      "percentageChangePi_14d": -18.53831,
      "percentageChangePi_30d": -25.91149,
      "percentageChangePi_60d": -23.88185,
      "percentageChangePi_200d": -55.13901,
      "percentageChangePi_1y": -40.96043,
      "percentageChangePi_GBP": -5.70077,
      "percentageChangePi_GBP_7d": -18.26029,
      "percentageChangePi_GBP_14d": -19.92032,
      "percentageChangePi_GBP_30d": -27.12555,
      "percentageChangePi_GBP_60d": -25.90469,
      "percentageChangePi_GBP_200d": -56.03376,
      "percentageChangePi_GBP_1y": -46.58153
    }
  }
}
