{
  "pi-network": {
    "id": "pi-network",
    "symbol": "pi",
    "name": "Pi Network",
    "priceGBP": 0.331591,
    "marketCapGBP": 2558367855,
    "percentageChange": -0.95511,
    "high_24hGBP": 0.334789,
    "low_24hGBP": 0.327265,
    "lastUpdated": "2025-07-20T06:07:06.211Z",
    "allTimeHigh": {
      "priceGBP": 2.35,
      "percentageChange": -85.90023,
      "date": "2025-02-26T16:41:03.732Z"
    },
    "allTimeLow": {
      "priceGBP": 0.315895,
      "percentageChange": 5.01814,
      "date": "2025-04-05T04:50:37.033Z"
    },
    "priceChange": {
      "pricePi_24h": -0.0042889302414202,
      "priceGBP24h": -0.003197590496839819,
      "percentageChangePi_24h": -0.95511,
      "percentageChangePi_7d": -5.01997,
      "percentageChangePi_14d": -0.95479,
      "percentageChangePi_30d": -17.16533,
      "percentageChangePi_60d": -46.13807,
      "percentageChangePi_200d": 0.0,
      "percentageChangePi_1y": 0.0,
      "percentageChangePi_GBP": -0.95511,
      "percentageChangePi_GBP_7d": -4.41805,
      "percentageChangePi_GBP_14d": 0.8358,
      "percentageChangePi_GBP_30d": -16.65917,
      "percentageChangePi_GBP_60d": -46.0474,
      "percentageChangePi_GBP_200d": null,
      "percentageChangePi_GBP_1y": null
    }
  },
  "xrp": {
    "id": "ripple",
    "symbol": "xrp",
    "name": "XRP",
    "priceGBP": 2.55,
    "marketCapGBP": 150840683035,
    "percentageChange": -1.46469,
    "high_24hGBP": 2.59,
    "low_24hGBP": 2.51,
    "lastUpdated": "2025-07-20T06:08:13.000Z",
    "allTimeHigh": {
      "priceGBP": 2.76,
      "percentageChange": -7.782,
      "date": "2025-01-16T17:00:22.630Z"
    },
    "allTimeLow": {
      "priceGBP": 0.00159246,
      "percentageChange": 159980.60445,
      "date": "2014-05-22T00:00:00.000Z"
    },
    "priceChange": {
      "pricePi_24h": -0.050768265195928,
      "priceGBP24h": -0.0378500262755006,
      "percentageChangePi_24h": -1.46469,
      "percentageChangePi_7d": 23.19721,
      "percentageChangePi_14d": 53.66211,
      "percentageChangePi_30d": 58.78391,
      "percentageChangePi_60d": 43.38958,
      "percentageChangePi_200d": 59.81627,
      "percentageChangePi_1y": 480.16801,
      "percentageChangePi_GBP": -1.46469,
      "percentageChangePi_GBP_7d": 23.97795,
      "percentageChangePi_GBP_14d": 56.44009,
      "percentageChangePi_GBP_30d": 59.75417,
      "percentageChangePi_GBP_60d": 43.603,
      "percentageChangePi_GBP_200d": 49.12717,
      "percentageChangePi_GBP_1y": 458.71336
    }
  }
}
