{
  "pi-network": {
    "id": "pi-network",
    "symbol": "pi",
    "name": "Pi Network",
    "priceGBP": 0.094765,
    "marketCapGBP": 1017961934,
    "percentageChange": 1.22725,
    "high_24hGBP": 0.095267,
    "low_24hGBP": 0.093591,
    "lastUpdated": "2026-06-12T13:17:47.373Z",
    "allTimeHigh": {
      "priceGBP": 2.35,
      "percentageChange": -95.97232,
      "date": "2025-02-26T16:41:03.732Z"
    },
    "allTimeLow": {
      "priceGBP": 0.089087,
      "percentageChange": 6.37404,
      "date": "2026-06-06T05:05:45.511Z"
    },
    "priceChange": {
      "pricePi_24h": 0.00153904,
      "priceGBP24h": 0.00080491,
      "percentageChangePi_24h": 1.22725,
      "percentageChangePi_7d": 2.36036,
      "percentageChangePi_14d": -11.48257,
      "percentageChangePi_30d": -25.64945,
      "percentageChangePi_60d": -23.42024,
      "percentageChangePi_200d": -46.70453,
      "percentageChangePi_1y": -79.78212,
      "percentageChangePi_GBP": 0.85665,
      "percentageChangePi_GBP_7d": 2.60984,
      "percentageChangePi_GBP_14d": -11.26301,
      "percentageChangePi_GBP_30d": -25.12144,
      "percentageChangePi_GBP_60d": -23.18945,
      "percentageChangePi_GBP_200d": -47.83544,
      "percentageChangePi_GBP_1y": -79.48499
    }
  },
  "xrp": {
    "id": "ripple",
    "symbol": "xrp",
    "name": "XRP",
    "priceGBP": 0.846983,
    "marketCapGBP": 52565207081,
    "percentageChange": 1.8178,
    "high_24hGBP": 0.856264,
    "low_24hGBP": 0.828361,
    "lastUpdated": "2026-06-12T13:17:47.706Z",
    "allTimeHigh": {
      "priceGBP": 2.76,
      "percentageChange": -69.36047,
      "date": "2025-01-16T17:00:22.630Z"
    },
    "allTimeLow": {
      "priceGBP": 0.00159246,
      "percentageChange": 53086.95324,
      "date": "2014-05-22T00:00:00.000Z"
    },
    "priceChange": {
      "pricePi_24h": 0.02025651,
      "priceGBP24h": 0.01185428,
      "percentageChangePi_24h": 1.8178,
      "percentageChangePi_7d": 1.73607,
      "percentageChangePi_14d": -12.95938,
      "percentageChangePi_30d": -20.84575,
      "percentageChangePi_60d": -14.8123,
      "percentageChangePi_200d": -44.93932,
      "percentageChangePi_1y": -49.19378,
      "percentageChangePi_GBP": 1.41946,
      "percentageChangePi_GBP_7d": 1.98403,
      "percentageChangePi_GBP_14d": -12.74349,
      "percentageChangePi_GBP_30d": -20.28363,
      "percentageChangePi_GBP_60d": -14.54489,
      "percentageChangePi_GBP_200d": -46.1077,
      "percentageChangePi_GBP_1y": -48.37764
    }
  }
}
