{
  "pi-network": {
    "id": "pi-network",
    "symbol": "pi",
    "name": "Pi Network",
    "priceGBP": 0.152548,
    "marketCapGBP": 1277756462,
    "percentageChange": 1.24576,
    "high_24hGBP": 0.153742,
    "low_24hGBP": 0.150495,
    "lastUpdated": "2025-12-25T12:11:23.469Z",
    "allTimeHigh": {
      "priceGBP": 2.35,
      "percentageChange": -93.51681,
      "date": "2025-02-26T16:41:03.732Z"
    },
    "allTimeLow": {
      "priceGBP": 0.128875,
      "percentageChange": 18.36215,
      "date": "2025-10-10T21:25:41.582Z"
    },
    "priceChange": {
      "pricePi_24h": 0.00253313,
      "priceGBP24h": 0.00205269,
      "percentageChangePi_24h": 1.24576,
      "percentageChangePi_7d": 0.46787,
      "percentageChangePi_14d": -1.55377,
      "percentageChangePi_30d": -14.28422,
      "percentageChangePi_60d": -0.93048,
      "percentageChangePi_200d": -67.36651,
      "percentageChangePi_1y": 0.0,
      "percentageChangePi_GBP": 1.36395,
      "percentageChangePi_GBP_7d": -0.59914,
      "percentageChangePi_GBP_14d": -2.35577,
      "percentageChangePi_GBP_30d": -16.71418,
      "percentageChangePi_GBP_60d": -1.69465,
      "percentageChangePi_GBP_200d": -67.28819,
      "percentageChangePi_GBP_1y": null
    }
  },
  "xrp": {
    "id": "ripple",
    "symbol": "xrp",
    "name": "XRP",
    "priceGBP": 1.38,
    "marketCapGBP": 83397223650,
    "percentageChange": -0.47459,
    "high_24hGBP": 1.39,
    "low_24hGBP": 1.37,
    "lastUpdated": "2025-12-25T12:11:23.184Z",
    "allTimeHigh": {
      "priceGBP": 2.76,
      "percentageChange": -50.17035,
      "date": "2025-01-16T17:00:22.630Z"
    },
    "allTimeLow": {
      "priceGBP": 0.00159246,
      "percentageChange": 86398.95064,
      "date": "2014-05-22T00:00:00.000Z"
    },
    "priceChange": {
      "pricePi_24h": -0.0088566409668,
      "priceGBP24h": -0.00495023204112921,
      "percentageChangePi_24h": -0.47459,
      "percentageChangePi_7d": -0.82268,
      "percentageChangePi_14d": -7.79056,
      "percentageChangePi_30d": -15.81196,
      "percentageChangePi_60d": -29.80819,
      "percentageChangePi_200d": -16.01139,
      "percentageChangePi_1y": -19.25071,
      "percentageChangePi_GBP": -0.3584,
      "percentageChangePi_GBP_7d": -1.85436,
      "percentageChangePi_GBP_14d": -8.58396,
      "percentageChangePi_GBP_30d": -18.0925,
      "percentageChangePi_GBP_60d": -30.34962,
      "percentageChangePi_GBP_200d": -15.80983,
      "percentageChangePi_GBP_1y": -23.58033
    }
  }
}
